rpcoverredis/__init__.py
rpcoverredis/client.py
rpcoverredis/registry.py
rpcoverredis/rpcpyredis.py
rpcoverredis/server.py
rpcoverredis/example/__init__.py
rpcoverredis/example/client.py
rpcoverredis/example/server.py
rpcoverredis/resources/__init__.py
rpcpyredis-0.3.dist-info/METADATA
rpcpyredis-0.3.dist-info/WHEEL
rpcpyredis-0.3.dist-info/top_level.txt
rpcpyredis-0.3.dist-info/RECORD
