Metadata-Version: 2.1
Name: rpcpyredis
Version: 0.3
Summary: RPC over Redis
Home-page: UNKNOWN
Author: Ammar Voloder
License: UNKNOWN
Platform: UNKNOWN
Classifier: Programming Language :: Python :: 3
Classifier: License :: OSI Approved :: MIT License
Classifier: Operating System :: OS Independent
